screenshot_cleaner/__init__.py
screenshot_cleaner/cli.py
screenshot_cleaner/core/__init__.py
screenshot_cleaner/core/cleanup.py
screenshot_cleaner/core/platform.py
screenshot_cleaner/core/scanner.py
screenshot_cleaner/utils/__init__.py
screenshot_cleaner/utils/logging.py
screenshot_cleaner-1.1.0.dist-info/METADATA
screenshot_cleaner-1.1.0.dist-info/WHEEL
screenshot_cleaner-1.1.0.dist-info/entry_points.txt
screenshot_cleaner-1.1.0.dist-info/licenses/LICENSE
screenshot_cleaner-1.1.0.dist-info/RECORD
