Metadata-Version: 2.4
Name: screenshot-cleaner
Version: 1.1.0
Summary: A Python CLI tool for automatically cleaning up old macOS screenshots
Project-URL: Homepage, https://github.com/damienjburks/screenshot-cleaner
Project-URL: Documentation, https://github.com/damienjburks/screenshot-cleaner#readme
Project-URL: Repository, https://github.com/damienjburks/screenshot-cleaner
Project-URL: Issues, https://github.com/damienjburks/screenshot-cleaner/issues
Project-URL: Changelog, https://github.com/damienjburks/screenshot-cleaner/blob/main/CHANGELOG.md
Author-email: Screenshot Cleaner Contributors <contributors@example.com>
Maintainer-email: Screenshot Cleaner Contributors <contributors@example.com>
License: MIT
License-File: LICENSE
Keywords: automation,cleanup,cli,desktop,file-management,macos,screenshots
Classifier: Development Status :: 4 - Beta
Classifier: Environment :: Console
Classifier: Intended Audience :: Developers
Classifier: Intended Audience :: End Users/Desktop
Classifier: License :: OSI Approved :: MIT License
Classifier: Operating System :: MacOS
Classifier: Programming Language :: Python :: 3
Classifier: Programming Language :: Python :: 3.12
Classifier: Programming Language :: Python :: 3.13
Classifier: Topic :: System :: Filesystems
Classifier: Topic :: Utilities
Classifier: Typing :: Typed
Requires-Python: >=3.12
Requires-Dist: fire>=0.7.1
Requires-Dist: pytest-cov>=7.0.0
Requires-Dist: rich>=14.2.0
